{
  "version": "1.1",
  "source": "GeoNames (CC BY 4.0)",
  "source_url": "https://download.geonames.org/export/dump/",
  "country_code": "FR",
  "country_name": "France",
  "description": "France admin1 dictionary generated from GeoNames admin1CodesASCII.txt",
  "total_count": 13,
  "admin1_regions": {
    "11": {
      "country_code": "FR",
      "admin1_code": "11",
      "admin1_code_full": "FR.11",
      "admin1_name": "Île-de-France",
      "admin1_name_ascii": "Ile-de-France",
      "admin1_name_zh": "法兰西岛",
      "admin1_type": "Region",
      "aliases": [
        "Ile de France",
        "Ile-de-France",
        "Ilha de França",
        "Isla de Francia",
        "Région parisienne",
        "Région Île-de-France",
        "Île-de-France",
        "Île-de-France Region",
        "Іль-де-Франс",
        "Иль-де-Франс",
        "إيل دو فرانس",
        "ایل-دو-فرانس",
        "इल-दा-फ़्रान्स",
        "อิล-เดอ-ฟรองซ์",
        "イル・ド・フランス",
        "法兰西岛",
        "法兰西岛地区",
        "法兰西岛省",
        "일드프랑스"
      ],
      "geojson_key": "FR.11",
      "lat": 48.85341,
      "lng": 2.3488,
      "source": "geonames",
      "source_id": "3012874",
      "country_name": "France"
    },
    "24": {
      "country_code": "FR",
      "admin1_code": "24",
      "admin1_code_full": "FR.24",
      "admin1_name": "Centre-Val de Loire",
      "admin1_name_ascii": "Centre-Val de Loire",
      "admin1_name_zh": "中央-盧瓦爾河谷大區",
      "admin1_type": "Region",
      "aliases": [
        "Centre",
        "Centre-Val de Loire",
        "Centro",
        "Centro-Vale do Loire",
        "Centro-Valle de Loira",
        "Centro-Valle della Loira",
        "Merkez",
        "Region Centralny-Dolina Loary",
        "Regione Centrale",
        "Région Centre",
        "Région Centre-Val de Loire",
        "Центр — Долина Луари",
        "Центр — Долина Луары",
        "سانتر-فال دو لوار",
        "سانتر-وال دو لوآر",
        "सेंटर-वैल दे लोयर",
        "แคว้นซ็องทร์-วาลเดอลัวร์",
        "サントル＝ヴァル・ド・ロワール地域圏",
        "サントル＝ヴァル・ド・ロワール地域圏地区",
        "サントル＝ヴァル・ド・ロワール地域圏省",
        "中央-盧瓦爾河谷大區",
        "中央-盧瓦爾河谷大區地区",
        "中央-盧瓦爾河谷大區省",
        "상트르"
      ],
      "geojson_key": "FR.24",
      "lat": 47.39484,
      "lng": 0.70398,
      "source": "geonames",
      "source_id": "3027939",
      "country_name": "France"
    },
    "27": {
      "country_code": "FR",
      "admin1_code": "27",
      "admin1_code_full": "FR.27",
      "admin1_name": "Bourgogne",
      "admin1_name_ascii": "Bourgogne",
      "admin1_name_zh": "勃艮第-弗朗什-孔泰大區",
      "admin1_type": "Region",
      "aliases": [
        "BFC",
        "Borgogna-Franca Contea",
        "Borgonha-Franco-Condado",
        "Borgoña-Franco Condado",
        "Bourgogne",
        "Bourgogne-Franche-Comté",
        "Burgundia-Franche-Comté",
        "Бургундия — Франш-Конте",
        "Бургундія-Франш-Конте",
        "برغونية إفرنش كمته",
        "بورگوین-فرانش-کنته",
        "बोरगोग्न-फ़्रेन्च-कोम्टे",
        "แคว้นบูร์กอญ-ฟร็องช์-กงเต",
        "ブルゴーニュ＝フランシュ＝コンテ地域圏",
        "ブルゴーニュ＝フランシュ＝コンテ地域圏地区",
        "ブルゴーニュ＝フランシュ＝コンテ地域圏省",
        "勃艮第-弗朗什-孔泰大區",
        "勃艮第-弗朗什-孔泰大區地区",
        "勃艮第-弗朗什-孔泰大區省",
        "부르고뉴프랑슈콩테"
      ],
      "geojson_key": "FR.27",
      "lat": 47.31344,
      "lng": 5.01391,
      "source": "geonames",
      "source_id": "11071619",
      "country_name": "France"
    },
    "28": {
      "country_code": "FR",
      "admin1_code": "28",
      "admin1_code_full": "FR.28",
      "admin1_name": "Normandy",
      "admin1_name_ascii": "Normandy",
      "admin1_name_zh": "诺曼底大区",
      "admin1_type": "Region",
      "aliases": [
        "Normandia",
        "Normandie",
        "Normandiya",
        "Normandië",
        "Normandy",
        "Normandía",
        "Нормандия",
        "Нормандія",
        "نرماندی",
        "نرمندية",
        "नोर्मंडी",
        "แคว้นนอร์ม็องดี",
        "ノルマンディー地域圏",
        "ノルマンディー地域圏地区",
        "ノルマンディー地域圏省",
        "诺曼底",
        "诺曼底地区",
        "诺曼底大区",
        "诺曼底省",
        "노르망디"
      ],
      "geojson_key": "FR.28",
      "lat": 49.49346,
      "lng": 0.10785,
      "source": "geonames",
      "source_id": "11071621",
      "country_name": "France"
    },
    "32": {
      "country_code": "FR",
      "admin1_code": "32",
      "admin1_code_full": "FR.32",
      "admin1_name": "Hauts-de-France",
      "admin1_name_ascii": "Hauts-de-France",
      "admin1_name_zh": "上法兰西大区",
      "admin1_type": "Region",
      "aliases": [
        "Alta Francia",
        "Altos da França",
        "Hauts-de-France",
        "Nord-Pas-de-Calais",
        "Nord-Pas-de-Calais-Picardie",
        "Nord-Passo di Calais-Piccardia",
        "О-де-Франс",
        "أوت دو فرانس",
        "نور-پا-دو-کاله-پیکاردی",
        "हाउत्स-दे-फ्रांस",
        "แคว้นโอดฟร็องส์",
        "オー＝ド＝フランス地域圏",
        "オー＝ド＝フランス地域圏地区",
        "オー＝ド＝フランス地域圏省",
        "上法兰西",
        "上法兰西地区",
        "上法兰西大区",
        "上法兰西省",
        "오드프랑스"
      ],
      "geojson_key": "FR.32",
      "lat": 50.63391,
      "lng": 3.05512,
      "source": "geonames",
      "source_id": "11071624",
      "country_name": "France"
    },
    "44": {
      "country_code": "FR",
      "admin1_code": "44",
      "admin1_code_full": "FR.44",
      "admin1_name": "Grand Est",
      "admin1_name_ascii": "Grand Est",
      "admin1_name_zh": "大東部大區",
      "admin1_type": "Region",
      "aliases": [
        "Alsace-Champagne-Ardenne-Lorrain",
        "Alsace-Champagne-Ardenne-Lorraine",
        "Alsazia-Champagne-Ardenne-Lorena",
        "Gran Este",
        "Grand Est",
        "Grande Leste",
        "Lotharingen",
        "Гранд-Ест",
        "Гранд-Эст",
        "الشرق الكبير",
        "گرانت است",
        "ग्रांड एस्ट",
        "กร็อง อีส",
        "グラン・テスト地域圏",
        "グラン・テスト地域圏地区",
        "グラン・テスト地域圏省",
        "大東部大區",
        "大東部大區地区",
        "大東部大區省",
        "그랑테스트"
      ],
      "geojson_key": "FR.44",
      "lat": 48.58392,
      "lng": 7.74553,
      "source": "geonames",
      "source_id": "11071622",
      "country_name": "France"
    },
    "52": {
      "country_code": "FR",
      "admin1_code": "52",
      "admin1_code_full": "FR.52",
      "admin1_name": "Pays de la Loire",
      "admin1_name_ascii": "Pays de la Loire",
      "admin1_name_zh": "卢瓦尔河地区大区",
      "admin1_type": "Region",
      "aliases": [
        "Kraj Loary",
        "Paesi della Loira",
        "Pays de la Loire",
        "Pays de la Loire Region",
        "País do Loire",
        "Países del Loira",
        "Région Pays de la Loire",
        "Пеи-де-ла-Луар",
        "Пеї-де-ла-Луар",
        "بايي دو لا لوار",
        "پیی دو لا لوآر",
        "पेस़ दे ला लोइर",
        "แคว้นเปอีเดอลาลัวร์",
        "ペイ・ド・ラ・ロワール地域圏",
        "ペイ・ド・ラ・ロワール地域圏地区",
        "ペイ・ド・ラ・ロワール地域圏省",
        "卢瓦尔河地区",
        "卢瓦尔河地区地区",
        "卢瓦尔河地区大区",
        "卢瓦尔河地区省",
        "페이드라루아르"
      ],
      "geojson_key": "FR.52",
      "lat": 47.21725,
      "lng": -1.55336,
      "source": "geonames",
      "source_id": "2988289",
      "country_name": "France"
    },
    "53": {
      "country_code": "FR",
      "admin1_code": "53",
      "admin1_code_full": "FR.53",
      "admin1_name": "Brittany",
      "admin1_name_ascii": "Brittany",
      "admin1_name_zh": "布列塔尼大區",
      "admin1_type": "Region",
      "aliases": [
        "Bretagna",
        "Bretagne",
        "Bretanha",
        "Bretania",
        "Bretaña",
        "Bretonya",
        "Brittany",
        "Brittany Region",
        "Région Bretagne",
        "Бретань",
        "برطانية",
        "بریتانی",
        "ब्रतान्य",
        "แคว้นเบรอตาญ",
        "ブルターニュ地域圏",
        "ブルターニュ地域圏地区",
        "ブルターニュ地域圏省",
        "布列塔尼大區",
        "布列塔尼大區地区",
        "布列塔尼大區省",
        "브르타뉴"
      ],
      "geojson_key": "FR.53",
      "lat": 48.11109,
      "lng": -1.67431,
      "source": "geonames",
      "source_id": "3030293",
      "country_name": "France"
    },
    "75": {
      "country_code": "FR",
      "admin1_code": "75",
      "admin1_code_full": "FR.75",
      "admin1_name": "Nouvelle-Aquitaine",
      "admin1_name_ascii": "Nouvelle-Aquitaine",
      "admin1_name_zh": "",
      "admin1_type": "Region",
      "aliases": [
        "Aquitania-Limosino-Poitou-Charentes",
        "Nouvelle-Aquitaine",
        "누벨아키텐"
      ],
      "geojson_key": "FR.75",
      "lat": 44.84124,
      "lng": -0.58046,
      "source": "geonames",
      "source_id": "11071620",
      "country_name": "France"
    },
    "76": {
      "country_code": "FR",
      "admin1_code": "76",
      "admin1_code_full": "FR.76",
      "admin1_name": "Occitanie",
      "admin1_name_ascii": "Occitanie",
      "admin1_name_zh": "",
      "admin1_type": "Region",
      "aliases": [
        "Languedoc-Roussillon-Midi-Pyrénées",
        "Linguadoca-Rossiglione-Midi-Pirenei",
        "Occitanie",
        "Région Occitanie",
        "Région Occitanie (Pyrénées-Méditerranée)",
        "옥시타니"
      ],
      "geojson_key": "FR.76",
      "lat": 43.60426,
      "lng": 1.44367,
      "source": "geonames",
      "source_id": "11071623",
      "country_name": "France"
    },
    "84": {
      "country_code": "FR",
      "admin1_code": "84",
      "admin1_code_full": "FR.84",
      "admin1_name": "Rhône-Alpes",
      "admin1_name_ascii": "Rhone-Alpes",
      "admin1_name_zh": "奧弗涅-羅訥-阿爾卑斯大區",
      "admin1_type": "Region",
      "aliases": [
        "Alvernia-Rodano-Alpi",
        "Auvergne-Rhône-Alpes",
        "Auvernia-Ródano-Alpes",
        "Auvérnia-Ródano-Alpes",
        "Owernia-Rodan-Alpy",
        "Rhone-Alpes",
        "Rhône-Alpes",
        "Овернь — Рона — Альпы",
        "Овернь-Рона-Альпи",
        "أوفرن-رون ألب",
        "اوورنی-رون-آلپ",
        "ऑवेरगन-रोन-एल्प्स",
        "แคว้นโอแวร์ญ-โรนาลป์",
        "オーヴェルニュ＝ローヌ＝アルプ地域圏",
        "オーヴェルニュ＝ローヌ＝アルプ地域圏地区",
        "オーヴェルニュ＝ローヌ＝アルプ地域圏省",
        "奧弗涅-羅訥-阿爾卑斯大區",
        "奧弗涅-羅訥-阿爾卑斯大區地区",
        "奧弗涅-羅訥-阿爾卑斯大區省",
        "오베르뉴론알프"
      ],
      "geojson_key": "FR.84",
      "lat": 45.74906,
      "lng": 4.84789,
      "source": "geonames",
      "source_id": "11071625",
      "country_name": "France"
    },
    "93": {
      "country_code": "FR",
      "admin1_code": "93",
      "admin1_code_full": "FR.93",
      "admin1_name": "Provence-Alpes-Côte d'Azur",
      "admin1_name_ascii": "Provence-Alpes-Cote d'Azur",
      "admin1_name_zh": "普罗旺斯-阿尔卑斯-蔚蓝海岸大区",
      "admin1_type": "Region",
      "aliases": [
        "Provence",
        "Provence-Alpes-Cote d'Azur",
        "Provence-Alpes-Côte d'Azur",
        "Provence-Alpes-Côte d'Azur Region",
        "Provence-Alpes-Côte d’Azur",
        "Provenza-Alpes-Costa Azul",
        "Provenza-Alpi-Costa Azzurra",
        "Provença-Alpes-Costa Azul",
        "Prowansja-Alpy-Lazurowe Wybrzeże",
        "Région PACA",
        "Région Provence-Alpes-Côte d'Azur",
        "Прованс — Альпы — Лазурный Берег",
        "Прованс-Альпи-Лазурний берег",
        "إقليم ألب كوت دازور",
        "پروانس آلپ‌-کوت دازور",
        "प्रोवेंस-एल्पस-कोट डी'आज़ुर",
        "แคว้นพรอว็องซาลป์-โกตดาซูร์",
        "プロヴァンス＝アルプ＝コート・ダジュール地域圏",
        "プロヴァンス＝アルプ＝コート・ダジュール地域圏地区",
        "プロヴァンス＝アルプ＝コート・ダジュール地域圏省",
        "普罗旺斯-阿尔卑斯-蔚蓝海岸",
        "普罗旺斯-阿尔卑斯-蔚蓝海岸地区",
        "普罗旺斯-阿尔卑斯-蔚蓝海岸大区",
        "普罗旺斯-阿尔卑斯-蔚蓝海岸省",
        "프로방스알프코트다쥐르"
      ],
      "geojson_key": "FR.93",
      "lat": 43.29695,
      "lng": 5.38107,
      "source": "geonames",
      "source_id": "2985244",
      "country_name": "France"
    },
    "94": {
      "country_code": "FR",
      "admin1_code": "94",
      "admin1_code_full": "FR.94",
      "admin1_name": "Corsica",
      "admin1_name_ascii": "Corsica",
      "admin1_name_zh": "",
      "admin1_type": "Region",
      "aliases": [
        "Collectivité Territoriale de Corse",
        "Corse",
        "Corsica",
        "Corsica Region",
        "Korsika",
        "Région Corse",
        "Territorial Collectivity of Corsica",
        "قرسقة",
        "قرشقة",
        "قـُرْشِقَة",
        "قَرْسَقَة",
        "كورسكا",
        "كورسيكا",
        "كُورَسِكَا",
        "كُورَسِيكَا",
        "코르시카"
      ],
      "geojson_key": "FR.94",
      "lat": 41.91886,
      "lng": 8.73812,
      "source": "geonames",
      "source_id": "3023519",
      "country_name": "France"
    }
  }
}