{
  "version": "1.1",
  "source": "GeoNames (CC BY 4.0)",
  "source_url": "https://download.geonames.org/export/dump/",
  "country_code": "PH",
  "country_name": "Philippines",
  "description": "Philippines admin1 dictionary generated from GeoNames admin1CodesASCII.txt",
  "total_count": 17,
  "admin1_regions": {
    "01": {
      "country_code": "PH",
      "admin1_code": "01",
      "admin1_code_full": "PH.01",
      "admin1_name": "Ilocos",
      "admin1_name_ascii": "Ilocos",
      "admin1_name_zh": "伊羅戈",
      "admin1_type": "Admin1",
      "aliases": [
        "Ilocos",
        "Ilocos Bölgesi",
        "Ilocos Region",
        "Ilocosin alue",
        "Ilocosregionen",
        "Região de Ilocos",
        "Ілокос",
        "Илокос",
        "منطقه ایلوکوس",
        "इलोकोस क्षेत्र",
        "เขตอีโลโคส",
        "イロコス地方",
        "伊羅戈",
        "일로코스 지방"
      ],
      "geojson_key": "PH.01",
      "lat": 16.04313,
      "lng": 120.33325,
      "source": "geonames",
      "source_id": "7521301",
      "country_name": "Philippines"
    },
    "02": {
      "country_code": "PH",
      "admin1_code": "02",
      "admin1_code_full": "PH.02",
      "admin1_name": "Cagayan Valley",
      "admin1_name_ascii": "Cagayan Valley",
      "admin1_name_zh": "卡加延河谷",
      "admin1_type": "Admin1",
      "aliases": [
        "Cagayan Valley",
        "Cagayandalen",
        "Lembah Cagayan",
        "Thung lũng Cagayan",
        "Vale de Cagayan",
        "Valle del Cagayán",
        "Valle di Cagayan",
        "Vallée de Cagayan",
        "Долина Кагаян",
        "دره کاگایان",
        "وادي كاغيان",
        "कागायान घाटी",
        "เขตลัมบักนางคากายัน",
        "カガヤン・バレー地方",
        "卡加延河谷",
        "카가얀밸리 지방"
      ],
      "geojson_key": "PH.02",
      "lat": 17.61577,
      "lng": 121.72285,
      "source": "geonames",
      "source_id": "7521297",
      "country_name": "Philippines"
    },
    "03": {
      "country_code": "PH",
      "admin1_code": "03",
      "admin1_code_full": "PH.03",
      "admin1_name": "Central Luzon",
      "admin1_name_ascii": "Central Luzon",
      "admin1_name_zh": "中央吕宋",
      "admin1_type": "Admin1",
      "aliases": [
        "Central Luzon",
        "Centrala Luzon",
        "Keski-Luzon",
        "Luzon Central",
        "Luzon Centrale",
        "Luzon Tengah",
        "Luzon Środkowy",
        "Luzón Central",
        "Luçon centrale",
        "Merkez Luzon",
        "Trung Luzon",
        "Центральний Лусон",
        "Центральный Лусон",
        "سنترال لوزون",
        "मध्य लूज़ोन",
        "เขตกิตนางลูโซน",
        "中央吕宋",
        "中部ルソン地方",
        "중앙루손 지방"
      ],
      "geojson_key": "PH.03",
      "lat": 15.15,
      "lng": 120.58333,
      "source": "geonames",
      "source_id": "7521305",
      "country_name": "Philippines"
    },
    "05": {
      "country_code": "PH",
      "admin1_code": "05",
      "admin1_code_full": "PH.05",
      "admin1_name": "Bicol Region",
      "admin1_name_ascii": "Bicol Region",
      "admin1_name_zh": "比科爾",
      "admin1_type": "Admin1",
      "aliases": [
        "Bicol",
        "Bicol Region",
        "Bicol-Region",
        "Bicolandia",
        "Bicolin alue",
        "Bikolregionen",
        "Região de Bicol",
        "Бикольский Регион",
        "Бікол",
        "منطقه بیکل",
        "बिकोल क्षेत्र",
        "เขตบีโคล",
        "ビコル地方",
        "比科爾",
        "비콜 지방"
      ],
      "geojson_key": "PH.05",
      "lat": 12.97389,
      "lng": 123.99333,
      "source": "geonames",
      "source_id": "7521310",
      "country_name": "Philippines"
    },
    "06": {
      "country_code": "PH",
      "admin1_code": "06",
      "admin1_code_full": "PH.06",
      "admin1_name": "Western Visayas",
      "admin1_name_ascii": "Western Visayas",
      "admin1_name_zh": "西米沙鄢",
      "admin1_type": "Admin1",
      "aliases": [
        "Batı Visayas",
        "Bisayas Occidentales",
        "Länsi-Visayas",
        "Tây Visayas",
        "Visayas Barat",
        "Visayas Occidentale",
        "Visayas Ocidentais",
        "Visayas occidentales",
        "Västra Visayas",
        "Western Visayas",
        "Западные Висайи",
        "Західні Вісаї",
        "بيسايا الغربية",
        "وسترن ویسایاز",
        "पश्चिमी विसाया",
        "เขตคันลูรังคาบีซายาอัน",
        "西ヴィサヤ地方",
        "西米沙鄢",
        "서비사야스 지방"
      ],
      "geojson_key": "PH.06",
      "lat": 10.69694,
      "lng": 122.56444,
      "source": "geonames",
      "source_id": "7521304",
      "country_name": "Philippines"
    },
    "07": {
      "country_code": "PH",
      "admin1_code": "07",
      "admin1_code_full": "PH.07",
      "admin1_name": "Central Visayas",
      "admin1_name_ascii": "Central Visayas",
      "admin1_name_zh": "中米沙鄢",
      "admin1_type": "Admin1",
      "aliases": [
        "Bisayas Centrales",
        "Central Visayas",
        "Centrala Visayas",
        "Keski-Visayas",
        "Merkez Visayas",
        "Region VII",
        "Trung Visayas",
        "Visayas Centrais",
        "Visayas Centrale",
        "Visayas Tengah",
        "Visayas centrales",
        "Центральные Висайи",
        "Центральні Вісаї",
        "بيسايا الوسطى",
        "سنترال ویسایاز",
        "मध्य विसाया",
        "เขตกิตนางคาบีซายาอัน",
        "中米沙鄢",
        "中部ヴィサヤ地方",
        "중앙비사야스 지방"
      ],
      "geojson_key": "PH.07",
      "lat": 10.31672,
      "lng": 123.89071,
      "source": "geonames",
      "source_id": "7521306",
      "country_name": "Philippines"
    },
    "08": {
      "country_code": "PH",
      "admin1_code": "08",
      "admin1_code_full": "PH.08",
      "admin1_name": "Eastern Visayas",
      "admin1_name_ascii": "Eastern Visayas",
      "admin1_name_zh": "東米沙鄢",
      "admin1_type": "Admin1",
      "aliases": [
        "Bisayas Orientales",
        "Doğu Visayas",
        "Eastern Visayas",
        "Itä-Visayas",
        "Region VIII",
        "Visayas Orientais",
        "Visayas Orientale",
        "Visayas Timur",
        "Visayas orientales",
        "Östra Visayas",
        "Đông Visayas",
        "Восточные Висайи",
        "Східні Вісаї",
        "पूर्वी विसाया",
        "เขตซีลางังคาบีซายาอัน",
        "東ヴィサヤ地方",
        "東米沙鄢",
        "동비사야스 지방"
      ],
      "geojson_key": "PH.08",
      "lat": 11.24333,
      "lng": 125.00472,
      "source": "geonames",
      "source_id": "7521307",
      "country_name": "Philippines"
    },
    "09": {
      "country_code": "PH",
      "admin1_code": "09",
      "admin1_code_full": "PH.09",
      "admin1_name": "Zamboanga Peninsula",
      "admin1_name_ascii": "Zamboanga Peninsula",
      "admin1_name_zh": "三宝颜半岛",
      "admin1_type": "Admin1",
      "aliases": [
        "Bán đảo Zamboanga",
        "Penisola di Zamboanga",
        "Península de Zamboanga",
        "Region IX",
        "Zamboanga Peninsula",
        "Zamboanga Yarımadası",
        "Zamboangahalvön",
        "Zamboangan niemimaa",
        "péninsule de Zamboanga",
        "semenanjung Sembuangan",
        "Полуостров Замбоанга",
        "Півострів Замбоанга",
        "شبه جزيرة زامبوانجا",
        "شبه جزیره زامبوانگا",
        "ज़म्बोआंगा प्रायद्वीप",
        "เขตตังไวนางซัมบวงกา",
        "サンボアンガ半島地方",
        "三宝颜半岛",
        "삼보앙가반도 지방"
      ],
      "geojson_key": "PH.09",
      "lat": 6.91028,
      "lng": 122.07389,
      "source": "geonames",
      "source_id": "7521308",
      "country_name": "Philippines"
    },
    "10": {
      "country_code": "PH",
      "admin1_code": "10",
      "admin1_code_full": "PH.10",
      "admin1_name": "Northern Mindanao",
      "admin1_name_ascii": "Northern Mindanao",
      "admin1_name_zh": "北棉兰老",
      "admin1_type": "Admin1",
      "aliases": [
        "Bắc Mindanao",
        "Mindanao Północne",
        "Mindanao Setentrional",
        "Mindanao Settentrionale",
        "Mindanao Utara",
        "Mindanao del Norte",
        "Mindanao du Nord",
        "Nord-Mindanao",
        "Norra Mindanao",
        "Northern Mindanao",
        "Pohjois-Mindanaon alue",
        "Північне Мінданао",
        "Северный Минданао",
        "مينداناو الشمالية",
        "उत्तरी मिन्दनाओ",
        "เขตฮีลากังมินดาเนา",
        "北ミンダナオ地方",
        "北棉兰老",
        "북민다나오 지방"
      ],
      "geojson_key": "PH.10",
      "lat": 8.48222,
      "lng": 124.64722,
      "source": "geonames",
      "source_id": "7521295",
      "country_name": "Philippines"
    },
    "11": {
      "country_code": "PH",
      "admin1_code": "11",
      "admin1_code_full": "PH.11",
      "admin1_name": "Davao Region",
      "admin1_name_ascii": "Davao Region",
      "admin1_name_zh": "达沃区",
      "admin1_type": "Admin1",
      "aliases": [
        "Davao",
        "Davao Bölgesi",
        "Davao Region",
        "Davaon alue",
        "Davaoregionen",
        "Região de Dávao",
        "Región de Dávao",
        "Vùng Davao",
        "Давао",
        "منطقه داوائو",
        "दावाओ क्षेत्र",
        "เขตดาเบา",
        "ダバオ地方",
        "达沃",
        "达沃区",
        "다바오 지방"
      ],
      "geojson_key": "PH.11",
      "lat": 7.07306,
      "lng": 125.61278,
      "source": "geonames",
      "source_id": "7521309",
      "country_name": "Philippines"
    },
    "12": {
      "country_code": "PH",
      "admin1_code": "12",
      "admin1_code_full": "PH.12",
      "admin1_name": "Soccsksargen",
      "admin1_name_ascii": "Soccsksargen",
      "admin1_name_zh": "索科斯克薩爾根",
      "admin1_type": "Admin1",
      "aliases": [
        "Mindanao Central",
        "Region XII",
        "Soccsksargen",
        "СОККСКСАРХЕН",
        "Сокксксарген",
        "सोकसारजेन",
        "เขตโซกซาร์เจน",
        "ソクサージェン地方",
        "索科斯克薩爾根",
        "소크사르젠 지방"
      ],
      "geojson_key": "PH.12",
      "lat": 7.16083,
      "lng": 124.475,
      "source": "geonames",
      "source_id": "7521298",
      "country_name": "Philippines"
    },
    "13": {
      "country_code": "PH",
      "admin1_code": "13",
      "admin1_code_full": "PH.13",
      "admin1_name": "Caraga",
      "admin1_name_ascii": "Caraga",
      "admin1_name_zh": "卡拉加区",
      "admin1_type": "Admin1",
      "aliases": [
        "Caraga",
        "Карага",
        "كاراجا",
        "कारागा",
        "เขตคารากา",
        "カラガ地方",
        "卡拉加",
        "卡拉加区",
        "카라가 지방"
      ],
      "geojson_key": "PH.13",
      "lat": 8.94917,
      "lng": 125.54361,
      "source": "geonames",
      "source_id": "7521299",
      "country_name": "Philippines"
    },
    "14": {
      "country_code": "PH",
      "admin1_code": "14",
      "admin1_code_full": "PH.14",
      "admin1_name": "Autonomous Region in Muslim Mindanao",
      "admin1_name_ascii": "Autonomous Region in Muslim Mindanao",
      "admin1_name_zh": "棉兰老穆斯林自治区",
      "admin1_type": "Admin1",
      "aliases": [
        "Autonomous Region in Muslim Mindanao",
        "Khu tự trị Hồi giáo Mindanao",
        "Mindanao Musulmán",
        "Mindanaon autonominen muslimialue",
        "Muslimska Mindanao",
        "Muzułmańskie Mindanao",
        "Müslüman Mindanao Özerk Bölgesi",
        "Regione Autonoma nel Mindanao Musulmano",
        "Região Autónoma do Mindanau Muçulmano",
        "Région autonome en Mindanao musulmane",
        "Автономный регион в Мусульманском Минданао",
        "イスラム教徒ミンダナオ自治地域",
        "棉兰老穆斯林",
        "棉兰老穆斯林自治区",
        "무슬림 민다나오 자치구"
      ],
      "geojson_key": "PH.14",
      "lat": 7.20417,
      "lng": 124.43972,
      "source": "geonames",
      "source_id": "7115989",
      "country_name": "Philippines"
    },
    "15": {
      "country_code": "PH",
      "admin1_code": "15",
      "admin1_code_full": "PH.15",
      "admin1_name": "Cordillera",
      "admin1_name_ascii": "Cordillera",
      "admin1_name_zh": "科迪勒拉行政區",
      "admin1_type": "Admin1",
      "aliases": [
        "Cordillera",
        "Cordillera Administrative",
        "Cordillera Administrative Region",
        "Cordilleran hallinnollinen alue",
        "Kordiljärernas administrativa",
        "Kordiljärernas administrativa region",
        "La Cordillera",
        "Regione amministrativa Cordillera",
        "Região Administrativa de Cordillera",
        "Région administrative de la Cordillère",
        "Vùng Hành chính Cordillera",
        "Кордильерский административный регион",
        "Кордильєрський адміністративний регіон",
        "منطقه اداری کوردیلرا",
        "कोर्दिल्येरा प्रशासनिक क्षेत्र",
        "เขตบริหารคอร์ดิลเยรา",
        "コルディリェラ行政地域",
        "科迪勒拉行政區",
        "코르디예라 행정구"
      ],
      "geojson_key": "PH.15",
      "lat": 16.41639,
      "lng": 120.59306,
      "source": "geonames",
      "source_id": "7521300",
      "country_name": "Philippines"
    },
    "40": {
      "country_code": "PH",
      "admin1_code": "40",
      "admin1_code_full": "PH.40",
      "admin1_name": "Calabarzon",
      "admin1_name_ascii": "Calabarzon",
      "admin1_name_zh": "卡拉巴松",
      "admin1_type": "Admin1",
      "aliases": [
        "Calabarzon",
        "Calabarzón",
        "КАЛАБАРСОН",
        "Калабарсон",
        "كالابارزون",
        "کالابارزون",
        "कालाबारज़ोन",
        "เขตคาลาบาร์โซน",
        "カラバルソン地方",
        "卡拉巴松",
        "칼라바르손 지방"
      ],
      "geojson_key": "PH.40",
      "lat": 14.62578,
      "lng": 121.12251,
      "source": "geonames",
      "source_id": "7521303",
      "country_name": "Philippines"
    },
    "41": {
      "country_code": "PH",
      "admin1_code": "41",
      "admin1_code_full": "PH.41",
      "admin1_name": "Mimaropa",
      "admin1_name_ascii": "Mimaropa",
      "admin1_name_zh": "民马罗巴区",
      "admin1_type": "Admin1",
      "aliases": [
        "MIMAROPA",
        "Mimaropa",
        "Tagalas Sudoccidentales",
        "МИМАРОПА",
        "Мімаропа",
        "ميماروبا",
        "میماروپا",
        "मिमारोपा",
        "เขตมีมาโรปา",
        "ミマロパ地方",
        "民马罗巴",
        "民马罗巴区",
        "미마로파 지방"
      ],
      "geojson_key": "PH.41",
      "lat": 9.73917,
      "lng": 118.73528,
      "source": "geonames",
      "source_id": "7521296",
      "country_name": "Philippines"
    },
    "NCR": {
      "country_code": "PH",
      "admin1_code": "NCR",
      "admin1_code_full": "PH.NCR",
      "admin1_name": "National Capital Region",
      "admin1_name_ascii": "National Capital Region",
      "admin1_name_zh": "",
      "admin1_type": "Admin1",
      "aliases": [
        "Metro Manila",
        "National Capital",
        "National Capital Region"
      ],
      "geojson_key": "PH.NCR",
      "lat": 14.6488,
      "lng": 121.0509,
      "source": "geonames",
      "source_id": "7521311",
      "country_name": "Philippines"
    }
  }
}